pynepalgeo/__init__.py
pynepalgeo/nepal_districts.py
pynepalgeo/nepal_municipalities.py
pynepalgeo/nepal_provinces.py
pynepalgeo/overall_info.py
pynepalgeo/utils.py
pynepalgeo/dataset/__init__.py
pynepalgeo/dataset/alldataset/__init__.py
pynepalgeo/dataset/districts/__init__.py
pynepalgeo/dataset/municipalities/__init__.py
pynepalgeo/dataset/provinces/__init__.py
pynepalgeo-1.1.2.dist-info/LICENSE.txt
pynepalgeo-1.1.2.dist-info/METADATA
pynepalgeo-1.1.2.dist-info/WHEEL
pynepalgeo-1.1.2.dist-info/top_level.txt
pynepalgeo-1.1.2.dist-info/RECORD
