Metadata-Version: 2.1
Name: pynepalgeo
Version: 1.1.2
Summary: A Python package to get information about provinces, districts, and municipalities of Nepal
Home-page: https://github.com/smaheshacharya/nepal-geoinfo
Author: Mahesh Acharya
Author-email: mahesh01acharya@gmail.com
Classifier: Programming Language :: Python :: 3
Classifier: License :: OSI Approved :: MIT License
Classifier: Operating System :: OS Independent
Requires-Python: >=3.6
License-File: LICENSE.txt
